nillion_signatures_mock/__init__.py
nillion_signatures_mock/encryption.py
nillion_signatures_mock/key_gen.py
nillion_signatures_mock/sign.py
nillion_signatures_mock-0.1.1.dist-info/METADATA
nillion_signatures_mock-0.1.1.dist-info/WHEEL
nillion_signatures_mock-0.1.1.dist-info/top_level.txt
nillion_signatures_mock-0.1.1.dist-info/RECORD
